q3huff2.cp310-win_amd64.pyd
q3huff2-0.4.2.dist-info/COPYING
q3huff2-0.4.2.dist-info/METADATA
q3huff2-0.4.2.dist-info/WHEEL
q3huff2-0.4.2.dist-info/top_level.txt
q3huff2-0.4.2.dist-info/RECORD
